mhirano/__init__.py
mhirano/nn/__init__.py
mhirano/nn/attention.py
mhirano-0.1.0.dist-info/LICENSE
mhirano-0.1.0.dist-info/WHEEL
mhirano-0.1.0.dist-info/METADATA
mhirano-0.1.0.dist-info/RECORD
